jlvandenhout/automaton/__init__.py
jlvandenhout/automaton/core.py
jlvandenhout_automaton-0.1.0.dist-info/LICENSE
jlvandenhout_automaton-0.1.0.dist-info/METADATA
jlvandenhout_automaton-0.1.0.dist-info/WHEEL
jlvandenhout_automaton-0.1.0.dist-info/top_level.txt
jlvandenhout_automaton-0.1.0.dist-info/RECORD
