Metadata-Version: 2.1
Name: jlvandenhout-automaton
Version: 0.1.0
Summary: This package provides a simple automaton implementation for Python.
Home-page: https://gitlab.com/jlvandenhout/automaton
Author: J.L. van den Hout
License: UNKNOWN
Platform: UNKNOWN
Classifier: License :: OSI Approved :: GNU General Public License v3 (GPLv3)
Classifier: Operating System :: OS Independent
Classifier: Programming Language :: Python :: 3
Requires-Dist: jlvandenhout-graph (>=2.0)
